mistyfy/__init__.py
mistyfy/misty.py
mistyfy-2.0.6.dist-info/LICENSE
mistyfy-2.0.6.dist-info/METADATA
mistyfy-2.0.6.dist-info/WHEEL
mistyfy-2.0.6.dist-info/top_level.txt
mistyfy-2.0.6.dist-info/RECORD
