Metadata-Version: 2.1
Name: mistyfy
Version: 2.0.6
Summary: A package that helps encrypt any given string and returns an encrypted string with a signed hash.This data can be sent over the internet and only you will know how to decrypt it because you control the cipher.
Home-page: https://github.com/princenyeche/mistyfy
Author: Prince Nyeche
Author-email: support@elfapp.website
License: UNKNOWN
Platform: UNKNOWN
Classifier: Programming Language :: Python :: 3
Classifier: License :: OSI Approved :: MIT License
Classifier: Operating System :: OS Independent
Requires-Python: >=3.6
